moby.py
moby-0.0.3.dist-info/DESCRIPTION.rst
moby-0.0.3.dist-info/METADATA
moby-0.0.3.dist-info/RECORD
moby-0.0.3.dist-info/WHEEL
moby-0.0.3.dist-info/entry_points.txt
moby-0.0.3.dist-info/metadata.json
moby-0.0.3.dist-info/top_level.txt
moby-0.0.3.dist-info/zip-safe
