Metadata-Version: 2.0
Name: moby
Version: 0.0.3
Summary: Tool to automate running commands in docker.
Home-page: https://github.com/siebz0r/moby
Author: Siebe Joris Jochems
Author-email: siebz0r@gmail.com
License: UNKNOWN
Keywords: docker,moby
Platform: UNKNOWN
Requires-Dist: docker
Requires-Dist: pyyaml
